pygccxml/__init__.py
pygccxml/declarations/__init__.py
pygccxml/declarations/algorithm.py
pygccxml/declarations/algorithms_cache.py
pygccxml/declarations/byte_info.py
pygccxml/declarations/call_invocation.py
pygccxml/declarations/calldef.py
pygccxml/declarations/calldef_members.py
pygccxml/declarations/calldef_types.py
pygccxml/declarations/class_declaration.py
pygccxml/declarations/comment.py
pygccxml/declarations/container_traits.py
pygccxml/declarations/cpptypes.py
pygccxml/declarations/decl_factory.py
pygccxml/declarations/decl_printer.py
pygccxml/declarations/decl_visitor.py
pygccxml/declarations/declaration.py
pygccxml/declarations/declaration_utils.py
pygccxml/declarations/declarations_matchers.py
pygccxml/declarations/dependencies.py
pygccxml/declarations/elaborated_info.py
pygccxml/declarations/enumeration.py
pygccxml/declarations/free_calldef.py
pygccxml/declarations/function_traits.py
pygccxml/declarations/has_operator_matcher.py
pygccxml/declarations/location.py
pygccxml/declarations/matchers.py
pygccxml/declarations/mdecl_wrapper.py
pygccxml/declarations/namespace.py
pygccxml/declarations/pattern_parser.py
pygccxml/declarations/pointer_traits.py
pygccxml/declarations/runtime_errors.py
pygccxml/declarations/scopedef.py
pygccxml/declarations/templates.py
pygccxml/declarations/traits_impl_details.py
pygccxml/declarations/type_traits.py
pygccxml/declarations/type_traits_classes.py
pygccxml/declarations/type_visitor.py
pygccxml/declarations/typedef.py
pygccxml/declarations/variable.py
pygccxml/declarations/xml_generators.py
pygccxml/parser/__init__.py
pygccxml/parser/config.py
pygccxml/parser/declarations_cache.py
pygccxml/parser/declarations_joiner.py
pygccxml/parser/directory_cache.py
pygccxml/parser/etree_scanner.py
pygccxml/parser/linker.py
pygccxml/parser/patcher.py
pygccxml/parser/project_reader.py
pygccxml/parser/scanner.py
pygccxml/parser/source_reader.py
pygccxml/utils/__init__.py
pygccxml/utils/utils.py
pygccxml/utils/xml_generators.py
pygccxml-3.0.2.dist-info/LICENSE.rst
pygccxml-3.0.2.dist-info/METADATA
pygccxml-3.0.2.dist-info/NOTICE
pygccxml-3.0.2.dist-info/WHEEL
pygccxml-3.0.2.dist-info/top_level.txt
pygccxml-3.0.2.dist-info/RECORD
