Metadata-Version: 2.2
Name: pygccxml
Version: 3.0.2
Summary: Python package for easy C++ declarations navigation.
Author-email: Michka Popoff <michkapopoff@gmail.com>, Insight Software Consortium <castxml@public.kitware.com>, Roman Yakovenko <romanyakovenko@gmail.com>
License: Boost Software License - Version 1.0 - August 17th, 2003
Project-URL: Homepage, https://github.com/CastXML/pygccxml
Project-URL: Documentation, https://readthedocs.org/projects/pygccxml/
Project-URL: Repository, https://github.com/CastXML/pygccxml
Project-URL: Changelog, https://github.com/CastXML/pygccxml/CHANGELOG.md
Keywords: C++,XML,declaration parser,CastXML,gccxml
Classifier: Development Status :: 5 - Production/Stable
Classifier: Environment :: Console
Classifier: Intended Audience :: Developers
Classifier: Operating System :: MacOS :: MacOS X
Classifier: Operating System :: Microsoft :: Windows
Classifier: Operating System :: POSIX
Classifier: Programming Language :: Python :: 3.9
Classifier: Programming Language :: Python :: 3.10
Classifier: Programming Language :: Python :: 3.11
Classifier: Programming Language :: Python :: 3.12
Classifier: Programming Language :: Python :: 3.13
Classifier: Programming Language :: Python :: Implementation :: CPython
Classifier: Programming Language :: Python :: Implementation :: PyPy
Classifier: Topic :: Software Development
License-File: LICENSE.rst
License-File: NOTICE
Requires-Dist: importlib-metadata>=4.6; python_version < "3.10"
Provides-Extra: test
Requires-Dist: coverage; extra == "test"
Requires-Dist: coveralls; extra == "test"
Requires-Dist: pycodestyle; extra == "test"
Requires-Dist: pytest; extra == "test"
Provides-Extra: docs
Requires-Dist: sphinx; extra == "docs"
Requires-Dist: sphinx_rtd_theme; extra == "docs"
Provides-Extra: examples
Requires-Dist: notebook; extra == "examples"
